rear/__init__.py
rear/rear.py
rear/scavenger.py
rear/test_rear.py
rear-0.1.2.dist-info/LICENSE
rear-0.1.2.dist-info/METADATA
rear-0.1.2.dist-info/WHEEL
rear-0.1.2.dist-info/entry_points.txt
rear-0.1.2.dist-info/top_level.txt
rear-0.1.2.dist-info/RECORD
