Metadata-Version: 2.1
Name: rear
Version: 0.1.2
Summary: Remote Archiver: safely collect output files into archives on network filesystem
Home-page: https://github.com/Contextualist/rear
Author: Contextualist
License: UNKNOWN
Platform: UNKNOWN
Classifier: Development Status :: 4 - Beta
Classifier: Framework :: Trio
Classifier: License :: OSI Approved :: MIT License
Classifier: Programming Language :: Python :: 3 :: Only
Classifier: Programming Language :: Python :: 3.8
Classifier: Programming Language :: Python :: 3.9
Classifier: Programming Language :: Python :: 3.10
Classifier: Topic :: System :: Archiving
Classifier: Topic :: System :: Distributed Computing
Classifier: Topic :: Utilities
Requires-Python: >=3.8
License-File: LICENSE
Requires-Dist: filelock (>=3.3.2)
Requires-Dist: trio
